parver/__init__.py
parver/_helpers.py
parver/_parse.py
parver/_segments.py
parver/_typing.py
parver/_version.py
parver/py.typed
parver-0.5.dist-info/LICENSE
parver-0.5.dist-info/METADATA
parver-0.5.dist-info/WHEEL
parver-0.5.dist-info/top_level.txt
parver-0.5.dist-info/RECORD
