Metadata-Version: 2.1
Name: parver
Version: 0.5
Summary: Parse and manipulate version numbers.
Author-email: Frazer McLean <frazer@frazermclean.co.uk>
License: MIT
Project-URL: Documentation, https://parver.readthedocs.io
Project-URL: Source Code, https://github.com/RazerM/parver
Keywords: pep440,version,parse
Classifier: Development Status :: 5 - Production/Stable
Classifier: Intended Audience :: Developers
Classifier: License :: OSI Approved :: MIT License
Classifier: Programming Language :: Python :: 3 :: Only
Classifier: Programming Language :: Python :: 3.8
Classifier: Programming Language :: Python :: 3.9
Classifier: Programming Language :: Python :: 3.10
Classifier: Programming Language :: Python :: 3.11
Classifier: Programming Language :: Python :: 3.12
Classifier: Programming Language :: Python :: Implementation :: CPython
Classifier: Programming Language :: Python :: Implementation :: PyPy
Requires-Python: >=3.8
License-File: LICENSE
Requires-Dist: arpeggio>=1.7
Requires-Dist: attrs>=19.2
Requires-Dist: typing-extensions; python_version < "3.10"
Provides-Extra: test
Requires-Dist: pytest; extra == "test"
Requires-Dist: hypothesis; extra == "test"
Requires-Dist: pretend; extra == "test"
Provides-Extra: docs
Requires-Dist: sphinx; extra == "docs"
Requires-Dist: furo; extra == "docs"
Provides-Extra: docstest
Requires-Dist: doc8; extra == "docstest"
Provides-Extra: pep8test
Requires-Dist: flake8; extra == "pep8test"
Requires-Dist: pep8-naming; extra == "pep8test"
